mcy_dist_ai/__init__.py
mcy_dist_ai/args.py
mcy_dist_ai/constants.py
mcy_dist_ai/exceptions.py
mcy_dist_ai/import_user_files.py
mcy_dist_ai/leader.py
mcy_dist_ai/logger.py
mcy_dist_ai/main.py
mcy_dist_ai/utils.py
mcy_dist_ai/worker.py
mcy_dist_ai/script/__init__.py
mcy_dist_ai/script/split_data.py
mcy_dist_ai-1.0.0.dist-info/LICENSE
mcy_dist_ai-1.0.0.dist-info/METADATA
mcy_dist_ai-1.0.0.dist-info/WHEEL
mcy_dist_ai-1.0.0.dist-info/entry_points.txt
mcy_dist_ai-1.0.0.dist-info/top_level.txt
mcy_dist_ai-1.0.0.dist-info/RECORD
