Metadata-Version: 2.1
Name: mcy-dist-ai
Version: 1.0.0
Summary: Mercury leader, worker and watcher
Home-page: https://github.com/mercury-protocol/mcy-sgx-gramine
Author: Peter Berekvolgyi
Author-email: peter@mercuryprotocol.io
Classifier: Programming Language :: Python :: 3
Classifier: License :: OSI Approved :: MIT License
Classifier: Operating System :: OS Independent
Requires-Python: >=3.10
License-File: LICENSE
Requires-Dist: torch ~=2.2.2
